civrealm/__init__.py
civrealm/game_ai_assistant.py
civrealm/parallel_tensor.py
civrealm/random_game.py
civrealm/random_game_minitask.py
civrealm/random_game_parallel.py
civrealm/random_game_self_play.py
civrealm/random_game_seq.py
civrealm/agents/__init__.py
civrealm/agents/base_agent.py
civrealm/agents/controller_agent.py
civrealm/agents/no_op_agent.py
civrealm/agents/random_agent.py
civrealm/agents/random_language_agent.py
civrealm/configs/__init__.py
civrealm/configs/dataset_settings.yaml
civrealm/configs/default_settings.yaml
civrealm/configs/docker-compose.yaml
civrealm/configs/llm_wrapper_settings.yaml
civrealm/configs/logging_config.py
civrealm/envs/__init__.py
civrealm/envs/freeciv_a3c_env.py
civrealm/envs/freeciv_base_env.py
civrealm/envs/freeciv_llm_env.py
civrealm/envs/freeciv_minitask_env.py
civrealm/envs/freeciv_parallel_env.py
civrealm/envs/freeciv_tensor_env.py
civrealm/envs/freeciv_tensor_minitask_env.py
civrealm/envs/parallel_self_play_env.py
civrealm/envs/parallel_tensor_env.py
civrealm/envs/self_play_env.py
civrealm/envs/freeciv_wrapper/__init__.py
civrealm/envs/freeciv_wrapper/action_wrapper.py
civrealm/envs/freeciv_wrapper/city_wrapper.py
civrealm/envs/freeciv_wrapper/config.py
civrealm/envs/freeciv_wrapper/core.py
civrealm/envs/freeciv_wrapper/dipl_wrapper.py
civrealm/envs/freeciv_wrapper/embark_wrapper.py
civrealm/envs/freeciv_wrapper/info_wrapper.py
civrealm/envs/freeciv_wrapper/llm_wrapper.py
civrealm/envs/freeciv_wrapper/mask_wrapper.py
civrealm/envs/freeciv_wrapper/observation_wrapper.py
civrealm/envs/freeciv_wrapper/reward_wrapper.py
civrealm/envs/freeciv_wrapper/tech_wrapper.py
civrealm/envs/freeciv_wrapper/tensor_base_wrapper.py
civrealm/envs/freeciv_wrapper/tensor_wrapper.py
civrealm/envs/freeciv_wrapper/utils.py
civrealm/exception/__init__.py
civrealm/exception/exceptions.py
civrealm/freeciv/__init__.py
civrealm/freeciv/build_server.py
civrealm/freeciv/civ_controller.py
civrealm/freeciv/clean.py
civrealm/freeciv/init_server.py
civrealm-0.1.2.dist-info/LICENSE
civrealm-0.1.2.dist-info/METADATA
civrealm-0.1.2.dist-info/WHEEL
civrealm-0.1.2.dist-info/entry_points.txt
civrealm-0.1.2.dist-info/top_level.txt
civrealm-0.1.2.dist-info/RECORD
