Metadata-Version: 2.1
Name: civrealm
Version: 0.1.2
Summary: CivRealm is an interactive environment for AI agents for the open-source strategy game Freeciv with the Freeciv-web client.
Author-email: Siyuan Qi <syqi@bigai.ai>, Shuo Chen <chenshuo@bigai.ai>, Yexin Li <liyexin@bigai.ai>, Xiangyu Kong <kongxiangyu@bigai.ai>, Pring Wong <huangping@bigai.ai>, Bangcheng Yang <yangbangcheng@bigai.ai>, Chris1869 <chris1869@github.com>, Junqi Wang <wangjunqi@bigai.ai>, Yifan Zhong <zhongyifan@bigai.ai>, Zhaowei Zhang <zhangzhaowei@bigai.ai>, Xiaoyuan Zhang <zhangxiaoyuan@bigai.ai>, Nian Liu <liunian@bigai.ai>
License: GLP3.0
Project-URL: Homepage, https://github.com/bigai-ai/civrealm
Project-URL: Issues, https://github.com/bigai-ai/civrealm/issues
Project-URL: Documentation, https://bigai-ai.github.io/civrealm/
Project-URL: Source, https://github.com/bigai-ai/civrealm
Keywords: civrealm,freeciv,ai,reinforcement-learning,openai-gym
Classifier: Development Status :: 5 - Production/Stable
Classifier: Programming Language :: Python :: 3
Classifier: Intended Audience :: Developers
Classifier: Intended Audience :: Education
Classifier: Intended Audience :: Science/Research
Classifier: Topic :: Scientific/Engineering :: Artificial Intelligence
Classifier: Topic :: Games/Entertainment :: Turn Based Strategy
Classifier: License :: OSI Approved :: GNU Lesser General Public License v3 (LGPLv3)
Requires-Python: >=3.8
License-File: LICENSE
Requires-Dist: importlib-resources
Requires-Dist: pyyaml >=5.4.1
Requires-Dist: overrides
Requires-Dist: wheel
Requires-Dist: docker
Requires-Dist: urllib3
Requires-Dist: BitVector
Requires-Dist: numpy
Requires-Dist: tornado ==6.3.2
Requires-Dist: gymnasium ==0.29.1
Requires-Dist: selenium ==4.9.1
Requires-Dist: websocket-client
Requires-Dist: filelock >=3.12.2
Requires-Dist: matplotlib
Requires-Dist: ray ==2.6.3 ; python_version < "3.12"
Provides-Extra: dev
Requires-Dist: pytest ; extra == 'dev'
Requires-Dist: pytest-xdist ; extra == 'dev'
